<?xml version="1.0"?>
<!DOCTYPE hibernate-mapping PUBLIC "-//Hibernate/Hibernate Mapping DTD 3.0//EN"
"http://www.hibernate.org/dtd/hibernate-mapping-3.0.dtd">
<!-- Generated 01-mar-2020 10:27:12 by Hibernate Tools 4.3.1 -->
<hibernate-mapping>
    <class name="POJOS.Configuracion" table="configuracion" catalog="bd_autobuses_gmt" optimistic-lock="version">
        <id name="idConfiguracion" type="java.lang.Integer">
            <column name="idConfiguracion" />
            <generator class="identity" />
        </id>
        <property name="nombre" type="string">
            <column name="nombre" length="50" not-null="true" />
        </property>
        <property name="cif" type="string">
            <column name="cif" length="50" not-null="true" />
        </property>
        <property name="telefono" type="int">
            <column name="telefono" not-null="true" />
        </property>
        <property name="usuario" type="string">
            <column name="usuario" length="20" not-null="true" />
        </property>
        <property name="password" type="string">
            <column name="password" length="200" not-null="true" />
        </property>
    </class>
</hibernate-mapping>
